LICENSE
README.md
setup.py
tls_client/__init__.py
tls_client/__version__.py
tls_client/cffi.py
tls_client/cookies.py
tls_client/exceptions.py
tls_client/response.py
tls_client/sessions.py
tls_client/settings.py
tls_client/structures.py
tls_client/dependencies/__init__.py
tls_client/dependencies/tls-client-32.dll
tls_client/dependencies/tls-client-64.dll
tls_client/dependencies/tls-client-amd64.so
tls_client/dependencies/tls-client-arm64.dylib
tls_client/dependencies/tls-client-arm64.so
tls_client/dependencies/tls-client-x86.dylib
tls_client/dependencies/tls-client-x86.so
tlsclient3.egg-info/PKG-INFO
tlsclient3.egg-info/SOURCES.txt
tlsclient3.egg-info/dependency_links.txt
tlsclient3.egg-info/top_level.txt